zboxfs/__init__.py
zboxfs-0.0.1.dist-info/LICENSE
zboxfs-0.0.1.dist-info/METADATA
zboxfs-0.0.1.dist-info/WHEEL
zboxfs-0.0.1.dist-info/top_level.txt
zboxfs-0.0.1.dist-info/RECORD
