Metadata-Version: 2.1
Name: zboxfs
Version: 0.0.1
Summary: ZboxFS binding for Python
Home-page: https://github.com/zboxfs/zbox
Author: Bo Lu
Author-email: support@zbox.io
License: UNKNOWN
Platform: UNKNOWN
Classifier: Programming Language :: Python :: 3
Classifier: License :: OSI Approved :: Apache Software License
Classifier: Operating System :: OS Independent
